skimpy_ext/__init__.py
skimpy_ext/skimpy.py
skimpy_ext-0.1.0.dist-info/LICENSE
skimpy_ext-0.1.0.dist-info/METADATA
skimpy_ext-0.1.0.dist-info/WHEEL
skimpy_ext-0.1.0.dist-info/RECORD
