Metadata-Version: 2.1
Name: skimpy-ext
Version: 0.1.0
Summary: 
Author: Luba
Author-email: luciano.eq@outlook.com
Requires-Python: >=3.10,<4.0
Classifier: Programming Language :: Python :: 3
Classifier: Programming Language :: Python :: 3.10
Classifier: Programming Language :: Python :: 3.11
Requires-Dist: polars (>=0.18.12,<0.19.0)
Requires-Dist: rich (==13.3.5)
